{"_id":{"$oid":"623412cd1bc479e2889b39d2"},"identifier":"foreyes:colocated","validLocationIds":[{"$numberInt":"5180494"},{"$numberInt":"5465444"},{"$numberInt":"5465495"},{"$numberInt":"5465521"},{"$numberInt":"5465538"},{"$numberInt":"5465582"},{"$numberInt":"5465560"},{"$numberInt":"5465607"},{"$numberInt":"5465638"},{"$numberInt":"5465684"}]}
{"_id":{"$oid":"623412cd1bc479e2889b39d3"},"identifier":"foreyes:standalone","validLocationIds":[{"$numberInt":"6136637"},{"$numberInt":"6172067"},{"$numberInt":"6136633"},{"$numberInt":"6136630"},{"$numberInt":"6136515"},{"$numberInt":"6101965"},{"$numberInt":"6172131"}]}
